{
	"name": "delete files older than some days",
	"properties": {
		"activities": [
			{
				"name": "Get Metadata1",
				"type": "GetMetadata",
				"dependsOn": [],
				"policy": {
					"timeout": "0.12:00:00",
					"retry": 0,
					"retryIntervalInSeconds": 30,
					"secureOutput": false,
					"secureInput": false
				},
				"userProperties": [],
				"typeProperties": {
					"dataset": {
						"referenceName": "ds_boblstorage1_result",
						"type": "DatasetReference"
					},
					"fieldList": [
						"childItems"
					],
					"storeSettings": {
						"type": "AzureBlobStorageReadSettings",
						"enablePartitionDiscovery": false
					},
					"formatSettings": {
						"type": "DelimitedTextReadSettings"
					}
				}
			},
			{
				"name": "ForEach1",
				"type": "ForEach",
				"dependsOn": [
					{
						"activity": "Get Metadata1",
						"dependencyConditions": [
							"Succeeded"
						]
					}
				],
				"userProperties": [],
				"typeProperties": {
					"items": {
						"value": "@activity('Get Metadata1').output.childItems",
						"type": "Expression"
					},
					"activities": [
						{
							"name": "Get Metadata2",
							"type": "GetMetadata",
							"dependsOn": [],
							"policy": {
								"timeout": "0.12:00:00",
								"retry": 0,
								"retryIntervalInSeconds": 30,
								"secureOutput": false,
								"secureInput": false
							},
							"userProperties": [],
							"typeProperties": {
								"dataset": {
									"referenceName": "ds_blobstorage_result",
									"type": "DatasetReference",
									"parameters": {
										"Filename": {
											"value": "@item().name",
											"type": "Expression"
										}
									}
								},
								"fieldList": [
									"itemName",
									"lastModified"
								],
								"storeSettings": {
									"type": "AzureBlobStorageReadSettings",
									"enablePartitionDiscovery": false
								},
								"formatSettings": {
									"type": "DelimitedTextReadSettings"
								}
							}
						},
						{
							"name": "If Condition1",
							"type": "IfCondition",
							"dependsOn": [
								{
									"activity": "Get Metadata2",
									"dependencyConditions": [
										"Succeeded"
									]
								}
							],
							"userProperties": [],
							"typeProperties": {
								"expression": {
									"value": "@less(activity('Get Metadata2').output.lastModified, \n    formatDateTime(adddays(utcNow(), -10), 'yyyy-MM-ddThh:mm:ssZ'))",
									"type": "Expression"
								},
								"ifFalseActivities": [
									{
										"name": "Set variable2",
										"type": "SetVariable",
										"dependsOn": [],
										"policy": {
											"secureOutput": false,
											"secureInput": false
										},
										"userProperties": [],
										"typeProperties": {
											"variableName": "File_name",
											"value": {
												"value": "@activity('Get Metadata2').output.lastModified",
												"type": "Expression"
											}
										}
									}
								],
								"ifTrueActivities": [
									{
										"name": "True",
										"type": "SetVariable",
										"dependsOn": [],
										"policy": {
											"secureOutput": false,
											"secureInput": false
										},
										"userProperties": [],
										"typeProperties": {
											"variableName": "File_name",
											"value": {
												"value": "@activity('Get Metadata2').output.lastModified",
												"type": "Expression"
											}
										}
									}
								]
							}
						}
					]
				}
			}
		],
		"variables": {
			"File_name": {
				"type": "String"
			}
		},
		"folder": {
			"name": "Delete Activity"
		},
		"annotations": []
	}
}